delayed_queue_manager/__init__.py
delayed_queue_manager/configuration.py
delayed_queue_manager/main.py
delayed_queue_manager/data/config.ini
delayed_queue_manager/static/css/styles.css
delayed_queue_manager/static/js/scripts.js
delayed_queue_manager/templates/index.html
delayed_queue_manager-1.1.1.dist-info/METADATA
delayed_queue_manager-1.1.1.dist-info/WHEEL
delayed_queue_manager-1.1.1.dist-info/top_level.txt
delayed_queue_manager-1.1.1.dist-info/RECORD
