Metadata-Version: 2.1
Name: delayed-queue-manager
Version: 1.1.1
Summary: Flask application which send the message after a delay implemented using socket
Home-page: https://github.com/lavvsharma/delayed_queue_manager
Author: Lav Sharma
Author-email: lavsharma2016@gmail.com
License: UNKNOWN
Platform: UNKNOWN
Classifier: Development Status :: 3 - Alpha
Classifier: Intended Audience :: Developers
Classifier: License :: OSI Approved :: MIT License
Classifier: Programming Language :: Python :: 3
Classifier: Programming Language :: Python :: 3.9
Requires-Dist: Flask >=3.0.3
Requires-Dist: flask-socketio >=5.3.6
Requires-Dist: configparser >=7.0.0
Requires-Dist: loguru >=0.7.2
